gitctx-0.1.1.dist-info/licenses/LICENSE
gitswitch/__init__.py
gitswitch/gitswitch.py
tests/__init__.py
tests/test_config.py
tests/test_gitswitch.py
gitctx-0.1.1.dist-info/METADATA
gitctx-0.1.1.dist-info/WHEEL
gitctx-0.1.1.dist-info/entry_points.txt
gitctx-0.1.1.dist-info/top_level.txt
gitctx-0.1.1.dist-info/RECORD
